bilibili/__init__.py
bilibili/cli/__init__.py
bilibili/cli/init.py
bilibili/cli/main.py
bilibili/cli/searcher.py
bilibili/cli/serve.py
bilibili/cli/test.py
bilibili/info/__init__.py
bilibili/utils/data_tool.py
ylz_bilibili-0.1.7.dist-info/METADATA
ylz_bilibili-0.1.7.dist-info/WHEEL
ylz_bilibili-0.1.7.dist-info/entry_points.txt
ylz_bilibili-0.1.7.dist-info/RECORD
